.coveragerc
.gitignore
.travis.yml
MANIFEST.in
README.rst
base.cfg
bootstrap.py
buildout.cfg
collective.videoanysurfer-configure.zcml
setup.py
travis.cfg
collective/__init__.py
collective.videoanysurfer.egg-info/PKG-INFO
collective.videoanysurfer.egg-info/SOURCES.txt
collective.videoanysurfer.egg-info/dependency_links.txt
collective.videoanysurfer.egg-info/entry_points.txt
collective.videoanysurfer.egg-info/namespace_packages.txt
collective.videoanysurfer.egg-info/not-zip-safe
collective.videoanysurfer.egg-info/requires.txt
collective.videoanysurfer.egg-info/top_level.txt
collective/videoanysurfer/__init__.py
collective/videoanysurfer/configure.zcml
collective/videoanysurfer/i18n.py
collective/videoanysurfer/testing.py
collective/videoanysurfer/upgrades.py
collective/videoanysurfer/upgrades.zcml
collective/videoanysurfer/video.py
collective/videoanysurfer/browser/__init__.py
collective/videoanysurfer/browser/configure.zcml
collective/videoanysurfer/browser/interfaces.py
collective/videoanysurfer/browser/jwplayer.js
collective/videoanysurfer/browser/jwplayer.pt
collective/videoanysurfer/browser/jwplayer.py
collective/videoanysurfer/browser/link_view.pt
collective/videoanysurfer/browser/link_view.py
collective/videoanysurfer/browser/nomensa.js
collective/videoanysurfer/browser/nomensa.pt
collective/videoanysurfer/browser/nomensa.py
collective/videoanysurfer/browser/vocabulary.py
collective/videoanysurfer/locales/collective.videoanysurfer.pot
collective/videoanysurfer/locales/en/LC_MESSAGES/collective.videoanysurfer.po
collective/videoanysurfer/locales/fr/LC_MESSAGES/collective.videoanysurfer.po
collective/videoanysurfer/locales/nl/LC_MESSAGES/collective.videoanysurfer.po
collective/videoanysurfer/profiles/default/browserlayer.xml
collective/videoanysurfer/profiles/default/jsregistry.xml
collective/videoanysurfer/profiles/default/metadata.xml
collective/videoanysurfer/profiles/default/registry.xml
collective/videoanysurfer/profiles/default/types.xml
collective/videoanysurfer/profiles/default/types/Link.xml
collective/videoanysurfer/tests/__init__.py
collective/videoanysurfer/tests/base.py
collective/videoanysurfer/tests/test_setup.py
docs/HISTORY.txt