Metadata-Version: 1.1
Name: collective.videoanysurfer
Version: 1.0.8
Summary: Youtube Integration to be AnySurfer compliant
Home-page: https://github.com/collective/collective.videoanysurfer
Author: JeanMichel FRANCOIS
Author-email: toutpt@gmail.com
License: GPL
Keywords: plone video anysurfer
Platform: UNKNOWN
Classifier: Programming Language :: Python
Classifier: Framework :: Plone
Classifier: Framework :: Plone :: 4.0
Classifier: Framework :: Plone :: 4.1
Classifier: Framework :: Plone :: 4.2
